rocrate_inveniordm/__init__.py
rocrate_inveniordm/deposit.py
rocrate_inveniordm/mapping/__init__.py
rocrate_inveniordm/mapping/condition_functions.py
rocrate_inveniordm/mapping/converter.py
rocrate_inveniordm/mapping/crate_utils.py
rocrate_inveniordm/mapping/mapping.json
rocrate_inveniordm/mapping/mapping_utils.py
rocrate_inveniordm/mapping/processing_functions.py
rocrate_inveniordm/upload/__init__.py
rocrate_inveniordm/upload/credentials.py
rocrate_inveniordm/upload/uploader.py
rocrate_inveniordm-2.1.0.dist-info/LICENSE
rocrate_inveniordm-2.1.0.dist-info/METADATA
rocrate_inveniordm-2.1.0.dist-info/WHEEL
rocrate_inveniordm-2.1.0.dist-info/entry_points.txt
rocrate_inveniordm-2.1.0.dist-info/RECORD
