Metadata-Version: 2.1
Name: rocrate-inveniordm
Version: 2.1.0
Summary: Upload RO-Crates to InvenioRDM and automatically fill the metadata. Supports any InvenioRDM instance, including Zenodo.
Home-page: https://www.researchobject.org/ro-crate/
License: MIT
Keywords: rocrate,RO-Crate,InvenioRDM,Zenodo
Author: Philipp Beer
Maintainer: Eli Chadwick
Maintainer-email: eli.chadwick@manchester.ac.uk
Requires-Python: >=3.8.1,<4.0.0
Classifier: Development Status :: 3 - Alpha
Classifier: License :: OSI Approved :: MIT License
Classifier: Programming Language :: Python :: 3
Classifier: Programming Language :: Python :: 3.9
Classifier: Programming Language :: Python :: 3.10
Classifier: Programming Language :: Python :: 3.11
Classifier: Programming Language :: Python :: 3.12
Classifier: Programming Language :: Python :: 3.8
Requires-Dist: python-dateutil (>=2.9.0,<3.0.0)
Requires-Dist: python-iso639 (>=2023.6.15)
Requires-Dist: pytz (>=2024.1)
Requires-Dist: requests (>=2.31.0,<3.0.0)
Project-URL: Issues, https://github.com/ResearchObject/ro-crate-inveniordm/issues
Project-URL: Repository, https://github.com/ResearchObject/ro-crate-inveniordm
